design.sv
//Name: Seongjae Shin
//Assignment: Final Project
//Purpose: Create a security system
//Date: May 6, 2021
//Module: proj_main, out_help
//Date of Last Update: May 6, 2021

// the code is 0100
module proj_main(S,X,U,Z);
  // S is swtich
  // X is user input (password entered)
  // U is update function for program. This always changes 0 to 1 or 1 to 0 to update program
  input S,X,U;
  // Z is 3 bits vertorization. Z[2] = Switch ON/OFF, Z[1] = Lock/Unlcok, Z[0] = Trigger/Not Trigger
  output [2:0]Z;
  
  // PS is present state
  reg [3:0] PS;
  // L is lock
  // if L = 0, it is unlocked, if L=1, it is locked
  reg L;
  
  // parameters for lock
  parameter unlock=1'b0, lock=1'b1;
  // parameters for present state
  parameter Ab=4'b0000,Bb=4'b0001,Cb=4'b0010,Db=4'b0011,Eb=4'b0100,Fb=4'b0101,Gb=4'b0110,Hb=4'b0111,Ib=4'b1000,Jb=4'b1001,Kb=4'b1010,Lb=4'b1011,Mb=4'b1100;
  // initially it is OFF and unlock
  initial PS=4'b0000;
  initial L=1'b0;
  // update when U is changed
  always@(U)
    // checking present state
    case(PS)
      //OFF
      Ab:if(S==1) PS=Bb;
      //ON
      Bb:if(S==0) PS=Ab; else if(S==1 && X==0) PS=Cb; else if(S==1 && X==1) PS=Ib;
      //First
      Cb:if(X==0) PS=Ib; else if(X==1) PS=Db;
      //Second
      Db:if(X==0) PS=Eb; else if(X==1) PS=Ib;
      //Third
      Eb:if(X==0) PS=Fb; else if(X==1) PS=Ib;
      //Fourth
      Fb:if(L==0) PS=Hb; else if(L==1) PS=Gb;
      //Unlock
      Gb:begin
        L=unlock;
        PS=Bb;
      end
      //Lock
      Hb:begin
        L=lock;
        PS=Bb;
      end
      //Trigger
      Ib:if(X==0) PS=Jb; else if(X==1) PS=Mb;
      //T-First
      Jb:if(X==0) PS=Mb; else if(X==1) PS=Kb;
      //T-Second
      Kb:if(X==0) PS=Lb; else if(X==1) PS=Mb;
      //T-Third
      Lb:PS=Bb;
      //Error
      Mb:PS=Ib;
    endcase
  
  // After change the present state based on the input, find the output corresponding state
  out_help out1(L,PS,Z);
  
endmodule

// helping function of output
module out_help(A,B,Z);
  // A is L, which is lock/unlock
  input A;
  // B is present state
  input [3:0]B;
  // Z is output of this system
  output [2:0] Z;
  // F is reg for output
  reg [2:0] F;
  
  // 6 enable outputs
  parameter F1=3'b000,F2=3'b010,F3=3'b100,F4=3'b110,F5=3'b101,F6=3'b111;
  // parameters for states
  parameter Ab=4'b0000,Bb=4'b0001,Cb=4'b0010,Db=4'b0011,Eb=4'b0100,Fb=4'b0101,Gb=4'b0110,Hb=4'b0111,Ib=4'b1000,Jb=4'b1001,Kb=4'b1010,Lb=4'b1011,Mb=4'b1100;
  // update output when state is changed
  always@(B)
    // check present state
    case(B)
      //OFF
      Ab:if(A==0) F=F1; else if(A==1) F=F2;
      //ON
      Bb:if(A==0) F=F3; else if(A==1) F=F4;
      //First
      Cb:if(A==0) F=F3; else if(A==1) F=F4;
      //Second
      Db:if(A==0) F=F3; else if(A==1) F=F4;
      //Third
      Eb:if(A==0) F=F3; else if(A==1) F=F4;
      //Fourth
      Fb:if(A==0) F=F3; else if(A==1) F=F4;
      //Unlock
      Gb:F=F3;
      //Lock
      Hb:F=F4;
      //Trigge
      Ib:if(A==0) F=F5; else if(A==1) F=F6;
      //T-First
      Jb:if(A==0) F=F5; else if(A==1) F=F6;
      //T-Second
      Kb:if(A==0) F=F5; else if(A==1) F=F6;
      //T-Third
      Lb:if(A==0) F=F5; else if(A==1) F=F6;
      //Error
      Mb:if(A==0) F=F5; else if(A==1) F=F6;
    endcase
  //assign reg F value into Z
  assign Z = F;
        
endmodule

testbench.sv
//Name: Seongjae Shin
//Assignment: Final Project
//Purpose: Test function
//Date: May 6, 2021
//Module: Final_test
//Date of Last Update: Mar 6, 2021


module Final_test;
  // set testbench reg and wire
  reg S_tb,X_tb,U_tb;
  wire [2:0] Z_tb;
  
  // reacll hw11_main to test
  proj_main test1(.S(S_tb),.X(X_tb),.U(U_tb),.Z(Z_tb));
  
  // set initial values of each input
  initial
    begin
      // Initially OFF
      U_tb=0;
      S_tb=0;
    end
  
  // Change 0 to 1 or 1 to 0 per given time
  always #1 U_tb=!U_tb;
	always
      begin
        //OFF->ON
		#1 S_tb=1;
        //ON->First
        #1 X_tb=0;
        //First->Second
        #1 X_tb=1;
        //Second->Third
        #1 X_tb=0;
        //Third->Fourth
        #1 X_tb=0;
        //Fourth->Lock
        #1 X_tb=0;
        //Lock->ON
        #1 X_tb=0;
        //ON->Trigger
        #1 X_tb=1;
        //Tigger->Error
        #1 X_tb=1;
        //Error->Trigger
        #1 X_tb=1;
        //Trigger->T-First
        #1 X_tb=0;
        //T-First->T-Second
        #1 X_tb=1;
        //T-Second->T-Third
        #1 X_tb=0;
        //T-third->ON
        #1 X_tb=0;
      	//ON->First
        #1 X_tb=0;
        //First->Second
        #1 X_tb=1;
        //Second->Third
        #1 X_tb=0;
        //Third->Foruth
        #1 X_tb=0;
        //Fourth->Unlock
        #1 X_tb=0;
        //Unlock->ON
        #1 X_tb=0;
      end
  
  // Set table, names and values of columns
  initial
    begin
      $display("S\t\X\t\U\t\tZ");
      $monitor("%b\t%b\t%b\t%b",S_tb,X_tb,U_tb,Z_tb);
    end
  
  // set waveform
  initial
    begin
      $dumpfile("Final.vcd");
      $dumpvars;
    end
  
  // set total timeer
  initial
    #20 $finish;
endmodule

Final.vcd
$date
	Thu May  6 23:10:58 2021
$end
$version
	Icarus Verilog
$end
$timescale
	1s
$end
$scope module Final_test $end
$var wire 3 ! Z_tb [2:0] $end
$var reg 1 " S_tb $end
$var reg 1 # U_tb $end
$var reg 1 $ X_tb $end
$scope module test1 $end
$var wire 1 " S $end
$var wire 1 # U $end
$var wire 1 $ X $end
$var wire 3 % Z [2:0] $end
$var reg 1 & L $end
$var reg 4 ' PS [3:0] $end
$scope module out1 $end
$var wire 1 & A $end
$var wire 4 ( B [3:0] $end
$var wire 3 ) Z [2:0] $end
$var reg 3 * F [2:0] $end
$upscope $end
$upscope $end
$upscope $end
$enddefinitions $end
#0
$dumpvars
b0 *
b0 )
b0 (
b0 '
0&
b0 %
x$
0#
0"
b0 !
$end
#1
b100 !
b100 %
b100 )
b100 *
b1 '
b1 (
1"
1#
#2
b10 '
b10 (
0$
0#
#3
b11 '
b11 (
1$
1#
#4
b100 '
b100 (
0$
0#
#5
b101 '
b101 (
1#
#6
b110 !
b110 %
b110 )
b110 *
b111 '
b111 (
0#
#7
b1 '
b1 (
1&
1#
#8
b111 !
b111 %
b111 )
b111 *
b1000 '
b1000 (
1$
0#
#9
b1100 '
b1100 (
1#
#10
b1000 '
b1000 (
0#
#11
b1001 '
b1001 (
0$
1#
#12
b1010 '
b1010 (
1$
0#
#13
b1011 '
b1011 (
0$
1#
#14
b110 !
b110 %
b110 )
b110 *
b1 '
b1 (
0#
#15
b10 '
b10 (
1#
#16
b11 '
b11 (
1$
0#
#17
b100 '
b100 (
0$
1#
#18
b101 '
b101 (
0#
#19
b100 !
b100 %
b100 )
b100 *
b110 '
b110 (
1#
#20
b1 '
b1 (
0&
0#
